{
    "data": {
        "Battery": {
            "": "Non-removable Li-Po battery (15.2 Wh)",
            "Stand-by": "",
            "Talk time": "Up to 10 h (multimedia)"
        },
        "Body": {
            "Dimensions": "209 x 123 x 8.5 mm (8.23 x 4.84 x 0.33 in)",
            "SIM": "Micro-SIM",
            "Weight": "350 g (12.35 oz)"
        },
        "Camera": {
            "Features": "Yes",
            "Primary": "5 MP, 2592 \u0445 1944 pixels, autofocus\n8 MP, 3264 x 2448 pixels, autofocus",
            "Secondary": "2 MP",
            "Video": "Yes"
        },
        "Comms": {
            "Bluetooth": "v4.0",
            "GPS": "Yes, with A-GPS, GLONASS",
            "Radio": "To be confirmed",
            "USB": "microUSB v2.0",
            "WLAN": "Wi-Fi 802.11 b/g/n, hotspot"
        },
        "Display": {
            "Multitouch": "Yes, up to 10 fingers",
            "Protection": "Oleophobic coating",
            "Resolution": "800 x 1280 pixels (~189 ppi pixel density)",
            "Size": "8.0 inches (~72.2% screen-to-body ratio)",
            "Type": "IPS LCD capacitive touchscreen, 16M colors"
        },
        "Features": {
            "": "- Google Drive (100 GB cloud storage)\n- MP3/WAV/eAAC+ player\n- MP4/H.264 player\n- Document viewer\n- Photo/video editor",
            "Browser": "HTML5",
            "Java": "No",
            "Messaging": "SMS(threaded view), MMS, Email, Push Mail, IM",
            "Sensors": "Accelerometer, proximity, compass"
        },
        "Launch": {
            "Announced": "2015, June",
            "Status": "Available. Released 2015, July"
        },
        "Memory": {
            "Card slot": "microSD, up to 64 GB",
            "Internal": "8 GB, 1 GB RAM\n16 GB, 2 GB RAM"
        },
        "Misc": {
            "0": "C",
            "1": "o",
            "10": ".",
            "11": "g",
            "12": "s",
            "13": "m",
            "14": "a",
            "15": "r",
            "16": "e",
            "17": "n",
            "18": "a",
            "19": ".",
            "2": "l",
            "20": "c",
            "21": "o",
            "22": "m",
            "23": "/",
            "24": "#",
            "3": "o",
            "4": "r",
            "5": "s",
            "6": "/",
            "7": "w",
            "8": "w",
            "9": "w"
        },
        "Network": {
            "2G bands": "GSM 850 / 900 / 1800 / 1900",
            "3G bands": "HSDPA 850 / 900 / 1900 / 2100",
            "4G bands": "LTE band 1(2100), 2(1900), 3(1800), 5(850), 7(2600), 8(900), 20(800)",
            "EDGE": "Yes",
            "GPRS": "Yes",
            "Speed": "HSPA, LTE Cat4 150/50 Mbps",
            "Technology": "GSM / HSPA / LTE"
        },
        "Platform": {
            "CPU": "Quad-core\nOcta-core",
            "Chipset": "Qualcomm MSM8916 Snapdragon 410\nQualcomm MSM8939 Snapdragon 615",
            "GPU": "Adreno 306\nAdreno 405",
            "OS": "Android OS, v5.0 (Lollipop)"
        },
        "Sound": {
            "": "- DTS sound",
            "3.5mm jack": "Yes",
            "Alert types": "Vibration; MP3, WAV ringtones",
            "Loudspeaker": "Yes"
        }
    },
    "main": {
        "device_name": "Asus ZenPad 8.0 Z380KL",
        "image": {
            "href": "http://www.gsmarena.com/asus_zenpad_8_0_z380kl-pictures-7255.php",
            "src": "http://cdn2.gsmarena.com/vv/bigpic/asus-zenpad-80.jpg"
        },
        "index": 1,
        "url": "http://www.gsmarena.com/asus_zenpad_8_0_z380kl-7255.php"
    }
}