{
    "data": {
        "Battery": {
            "": "Lithium ion 1200 mAh",
            "Stand-by": "240 h",
            "Talk time": "10 h"
        },
        "Body": {
            "Dimensions": "129 x 49 x 23 mm, 132 cc (5.08 x 1.93 x 0.91 in)",
            "SIM": "Mini-SIM",
            "Weight": "149 g (5.26 oz)"
        },
        "Camera": {},
        "Comms": {
            "Bluetooth": "No",
            "GPS": "Yes",
            "Infrared port": "Yes",
            "Radio": "No",
            "USB": "",
            "WLAN": "No"
        },
        "Display": {
            "": "- Electro-luminescent lighting\n- Dynamic & user-selectable font size",
            "Resolution": "100 x 48 pixels, 5 lines",
            "Size": "",
            "Type": "Monochrome graphic"
        },
        "Features": {
            "": "- Predictive text input\n- Organizer\n- Phone ON/OFF timers",
            "Alarm": "Yes",
            "Browser": "",
            "Clock": "Yes",
            "Games": "3",
            "Java": "No",
            "Messaging": "SMS"
        },
        "Launch": {
            "Announced": "2000",
            "Status": "Discontinued"
        },
        "Memory": {
            "Call records": "15 dialed, 10 received, 10 missed calls",
            "Card slot": "No",
            "Phonebook": "255"
        },
        "Misc": {
            "0": "C",
            "1": "o",
            "10": ".",
            "11": "g",
            "12": "s",
            "13": "m",
            "14": "a",
            "15": "r",
            "16": "e",
            "17": "n",
            "18": "a",
            "19": ".",
            "2": "l",
            "20": "c",
            "21": "o",
            "22": "m",
            "23": "/",
            "24": "#",
            "3": "o",
            "4": "r",
            "5": "s",
            "6": "/",
            "7": "w",
            "8": "w",
            "9": "w"
        },
        "Network": {
            "2G bands": "GSM 900 / 1800",
            "EDGE": "No",
            "GPRS": "No",
            "Technology": "GSM"
        },
        "Sound": {
            "": "- Personalised ringing melodies\n- Ascending alert\n- Several SMS alert tones and tone levels",
            "3.5mm jack": "No",
            "Alert types": "Vibration; Downloadable monophonic ringtones",
            "Loudspeaker": "No"
        }
    },
    "main": {
        "canonical_name": "GPS features, water and shock resistant",
        "device_name": "Benefon Track",
        "image": {
            "href": "http://www.gsmarena.com/benefon_track-pictures-43.php",
            "src": "http://cdn2.gsmarena.com/vv/bigpic/belocub.gif"
        },
        "index": 1,
        "url": "http://www.gsmarena.com/benefon_track-43.php"
    }
}