{
    "data": {
        "Battery": {
            "": "Li-Ion 1100 mAh battery",
            "Stand-by": "",
            "Talk time": ""
        },
        "Body": {
            "Dimensions": "112 x 58 x 14 mm (4.41 x 2.28 x 0.55 in)",
            "SIM": "Mini-SIM",
            "Weight": "137 g (4.83 oz)"
        },
        "Camera": {
            "Primary": "3.15 MP, 2048 x 1536 pixels, autofocus",
            "Secondary": "No",
            "Video": "No"
        },
        "Comms": {
            "Bluetooth": "v2.0, A2DP",
            "GPS": "Yes",
            "Radio": "No",
            "USB": "v2.0",
            "WLAN": "Wi-Fi 802.11b/g"
        },
        "Display": {
            "Resolution": "272 x 480 pixels (~155 ppi pixel density)",
            "Size": "3.55 inches (~53.7% screen-to-body ratio)",
            "Type": "TFT resistive touchscreen, 65K colors"
        },
        "Features": {
            "": "- Location-based applications\n- Organizer\n- World Clock\n- Document viewer (Word, Excel, PowerPoint, PDF)",
            "Browser": "HTTP / WAP 2.0",
            "Java": "Yes, MIDP 2.0",
            "Messaging": "SMS, MMS, Email, Push email, Instant Messaging"
        },
        "Launch": {
            "Announced": "2009, February. Released 2009, October",
            "Status": "Discontinued"
        },
        "Memory": {
            "Card slot": "microSD, up to 16 GB",
            "Internal": "4 GB, 128 MB RAM"
        },
        "Misc": {
            "Colors": "Black",
            "Price group": "4/10 (About 190 EUR)",
            "SAR US": "1.26 W/kg (head) \u00a0 \u00a0 0.37 W/kg (body)"
        },
        "Network": {
            "2G bands": "GSM 850 / 900 / 1800 / 1900",
            "3G bands": "HSDPA 850 / 900 / 2100",
            "EDGE": "Class 10",
            "GPRS": "Class 10",
            "Speed": "HSPA 3.6/0.384 Mbps",
            "Technology": "GSM / HSPA"
        },
        "Platform": {
            "0": "O",
            "1": "S",
            "10": ".",
            "11": "g",
            "12": "s",
            "13": "m",
            "14": "a",
            "15": "r",
            "16": "e",
            "17": "n",
            "18": "a",
            "19": ".",
            "2": "t",
            "20": "c",
            "21": "o",
            "22": "m",
            "23": "/",
            "24": "g",
            "25": "l",
            "26": "o",
            "27": "s",
            "28": "s",
            "29": "a",
            "3": "p",
            "30": "r",
            "31": "y",
            "32": ".",
            "33": "p",
            "34": "h",
            "35": "p",
            "36": "3",
            "37": "?",
            "38": "t",
            "39": "e",
            "4": ":",
            "40": "r",
            "41": "m",
            "42": "=",
            "43": "o",
            "44": "s",
            "5": "/",
            "6": "/",
            "7": "w",
            "8": "w",
            "9": "w"
        },
        "Sound": {
            "": "- 2.5 mm audio jack",
            "3.5mm jack": "No",
            "Alert types": "Vibration, MP3 ringtones",
            "Loudspeaker": "Yes"
        }
    },
    "main": {
        "device_name": "Garmin-Asus nuvifone G60",
        "image": {
            "href": "http://www.gsmarena.com/garmin_asus_nuvifone_g60-pictures-2725.php",
            "src": "http://cdn2.gsmarena.com/vv/bigpic/asus-nuvifone-g60.jpg"
        },
        "index": 1,
        "url": "http://www.gsmarena.com/garmin_asus_nuvifone_g60-2725.php"
    }
}