{
    "data": {
        "Battery": {
            "": "Li-Ion 650 mAh battery",
            "Stand-by": "",
            "Talk time": ""
        },
        "Body": {
            "": "- Flashlight",
            "Dimensions": "108 x 45.3 x 13.4 mm (4.25 x 1.78 x 0.53 in)",
            "SIM": "Mini-SIM",
            "Weight": "-"
        },
        "Camera": {},
        "Comms": {
            "Bluetooth": "No",
            "GPS": "No",
            "Radio": "FM radio",
            "USB": "No",
            "WLAN": "No"
        },
        "Display": {
            "Resolution": "128 x 128 pixels (~121 ppi pixel density)",
            "Size": "1.5 inches (~14.8% screen-to-body ratio)",
            "Type": "CSTN, 65K colors"
        },
        "Features": {
            "": "- Predictive text input",
            "Browser": "No",
            "Games": "No",
            "Java": "No",
            "Messaging": "SMS"
        },
        "Launch": {
            "Announced": "2010. Released 2010",
            "Status": "Discontinued"
        },
        "Memory": {
            "Call records": "Yes",
            "Card slot": "No",
            "Phonebook": "Yes"
        },
        "Misc": {
            "0": "C",
            "1": "o",
            "10": ".",
            "11": "g",
            "12": "s",
            "13": "m",
            "14": "a",
            "15": "r",
            "16": "e",
            "17": "n",
            "18": "a",
            "19": ".",
            "2": "l",
            "20": "c",
            "21": "o",
            "22": "m",
            "23": "/",
            "24": "#",
            "3": "o",
            "4": "r",
            "5": "s",
            "6": "/",
            "7": "w",
            "8": "w",
            "9": "w"
        },
        "Network": {
            "2G bands": "GSM 900 / 1800",
            "EDGE": "No",
            "GPRS": "No",
            "Technology": "GSM"
        },
        "Sound": {
            "3.5mm jack": "No",
            "Alert types": "Vibration; Polyphonic(64)",
            "Loudspeaker": "Yes"
        }
    },
    "main": {
        "device_name": "Haier M160",
        "image": {
            "href": "http://www.gsmarena.com/haier_m160-pictures-3378.php",
            "src": "http://cdn2.gsmarena.com/vv/bigpic/haier-m160.jpg"
        },
        "index": 1,
        "url": "http://www.gsmarena.com/haier_m160-3378.php"
    }
}