{
    "data": {
        "Battery": {
            "": "Li-Ion battery",
            "Stand-by": "Up to 150 h",
            "Talk time": "Up to 3 h"
        },
        "Body": {
            "Dimensions": "103.5 x 45 x 13.5 mm, 60 cc (4.07 x 1.77 x 0.53 in)",
            "SIM": "Mini-SIM",
            "Weight": "75 g (2.65 oz)"
        },
        "Camera": {},
        "Comms": {
            "Bluetooth": "No",
            "GPS": "No",
            "Radio": "No",
            "USB": "No",
            "WLAN": "No"
        },
        "Display": {
            "Resolution": "68 x 96 pixels (~84 ppi pixel density)",
            "Size": "1.4 inches (~12.8% screen-to-body ratio)",
            "Type": "Monochrome graphics"
        },
        "Features": {
            "": "- Predictive text input\n- Organizer\n- Push-To-Talk",
            "Browser": "No",
            "Games": "Yes",
            "Java": "No",
            "Messaging": "SMS"
        },
        "Launch": {
            "Announced": "2008",
            "Status": "Discontinued"
        },
        "Memory": {
            "": "- SMS storage up to 50 entries",
            "Call records": "10 dialed, 10 received, 10 missed calls",
            "Card slot": "No",
            "Phonebook": "100 entries"
        },
        "Misc": {
            "0": "C",
            "1": "o",
            "10": ".",
            "11": "g",
            "12": "s",
            "13": "m",
            "14": "a",
            "15": "r",
            "16": "e",
            "17": "n",
            "18": "a",
            "19": ".",
            "2": "l",
            "20": "c",
            "21": "o",
            "22": "m",
            "23": "/",
            "24": "#",
            "3": "o",
            "4": "r",
            "5": "s",
            "6": "/",
            "7": "w",
            "8": "w",
            "9": "w"
        },
        "Network": {
            "2G bands": "GSM 900 / 1800",
            "EDGE": "No",
            "GPRS": "No",
            "Technology": "GSM"
        },
        "Sound": {
            "3.5mm jack": "No",
            "Alert types": "Polyphonic(16) ringtones",
            "Loudspeaker": "Yes"
        }
    },
    "main": {
        "device_name": "Huawei T156",
        "index": 1,
        "url": "http://www.gsmarena.com/huawei_t156-2632.php"
    }
}