{
    "data": {
        "Battery": {
            "": "Li-Ion battery",
            "Stand-by": "Up to 160 h",
            "Talk time": "Up to 4 h"
        },
        "Body": {
            "Dimensions": "90 x 43 x 24 mm (3.54 x 1.69 x 0.94 in)",
            "SIM": "Mini-SIM",
            "Weight": "86 g (3.03 oz)"
        },
        "Camera": {
            "Primary": "1.3 MP, 1280 x 960 pixels, LED flash",
            "Secondary": "No",
            "Video": "Yes"
        },
        "Comms": {
            "Bluetooth": "No",
            "GPS": "No",
            "Infrared port": "Yes",
            "Radio": "No",
            "USB": "Yes",
            "WLAN": "No"
        },
        "Display": {
            "": "- Second external 65K colors CSTN display (96 x 64 pixels)\n- 4-way navi key",
            "Resolution": "128 x 160 pixels",
            "Size": "",
            "Type": "TFT, 256K colors"
        },
        "Features": {
            "": "- MP3/3GP player \n- Predictive text input\n- Voice memo\n- Bio-rhythm\n- Stopwatch",
            "Browser": "WAP 2.0/xHTML",
            "Games": "Yes + downloadable",
            "Java": "Yes, MIDP 2.0",
            "Messaging": "SMS, MMS, EMail"
        },
        "Launch": {
            "Announced": "2004, 4Q",
            "Status": "Discontinued"
        },
        "Memory": {
            "Call records": "20 received, dialed and missed calls",
            "Card slot": "No",
            "Internal": "128 MB",
            "Phonebook": "800 entries, Photo call"
        },
        "Misc": {
            "0": "C",
            "1": "o",
            "10": ".",
            "11": "g",
            "12": "s",
            "13": "m",
            "14": "a",
            "15": "r",
            "16": "e",
            "17": "n",
            "18": "a",
            "19": ".",
            "2": "l",
            "20": "c",
            "21": "o",
            "22": "m",
            "23": "/",
            "24": "#",
            "3": "o",
            "4": "r",
            "5": "s",
            "6": "/",
            "7": "w",
            "8": "w",
            "9": "w"
        },
        "Network": {
            "": "GSM 850 / 1900 - US version",
            "2G bands": "GSM 900 / 1800",
            "EDGE": "No",
            "GPRS": "Class 10",
            "Technology": "GSM"
        },
        "Sound": {
            "3.5mm jack": "No",
            "Alert types": "Vibration; Downloadable polyphonic, MP3 ringtones, composer",
            "Loudspeaker": "Yes"
        }
    },
    "main": {
        "device_name": "Innostream INNO A10",
        "image": {
            "href": "http://www.gsmarena.com/innostream_inno_a10-pictures-955.php",
            "src": "http://cdn2.gsmarena.com/vv/bigpic/ina10.gif"
        },
        "index": 1,
        "url": "http://www.gsmarena.com/innostream_inno_a10-955.php"
    }
}