{
    "data": {
        "Battery": {
            "": "Li-Ion 950 mAh battery",
            "Stand-by": "Up to 500 h",
            "Talk time": "Up to 5 h"
        },
        "Body": {
            "Dimensions": "103.7 x 47 x 15.6 mm (4.08 x 1.85 x 0.61 in)",
            "SIM": "Mini-SIM",
            "Weight": "79 g (2.79 oz)"
        },
        "Camera": {
            "Primary": "1.3 MP, 1280 x 1024 pixels",
            "Secondary": "No",
            "Video": ""
        },
        "Comms": {
            "Bluetooth": "v2.0, A2DP",
            "GPS": "No",
            "Radio": "FM radio",
            "USB": "Yes",
            "WLAN": "No"
        },
        "Display": {
            "Resolution": "120 x 160 pixels (~113 ppi pixel density)",
            "Size": "1.77 inches (~19.9% screen-to-body ratio)",
            "Type": "TFT, 65K colors"
        },
        "Features": {
            "": "- MP4/H.263 player\n- MP3/WAV/eAAC+ player\n- Predictive text input",
            "Browser": "WAP 2.0/xHTML",
            "Games": "Yes",
            "Java": "Yes, MIDP 2.0",
            "Messaging": "SMS, MMS, Email"
        },
        "Launch": {
            "Announced": "2009, March",
            "Status": "Available. Released 2009, May"
        },
        "Memory": {
            "Call records": "Yes",
            "Card slot": "microSD, up to 4 GB",
            "Internal": "4 MB",
            "Phonebook": "1000 entries, Photo call"
        },
        "Misc": {
            "Colors": "Black, Titan",
            "Price group": "1/10 (About 40 EUR)"
        },
        "Network": {
            "2G bands": "GSM 900 / 1800",
            "EDGE": "No",
            "GPRS": "Yes",
            "Technology": "GSM"
        },
        "Sound": {
            "3.5mm jack": "No",
            "Alert types": "Vibration; Downloadable polyphonic, MP3 ringtones",
            "Loudspeaker": "Yes"
        }
    },
    "main": {
        "device_name": "LG GB210",
        "image": {
            "href": "http://www.gsmarena.com/lg_gb210-pictures-2769.php",
            "src": "http://cdn2.gsmarena.com/vv/bigpic/lg-gb210.jpg"
        },
        "index": 1,
        "url": "http://www.gsmarena.com/lg_gb210-2769.php"
    }
}