{
    "data": {
        "Battery": {
            "": "NiMH 600 mAh battery",
            "Stand-by": "50 h",
            "Talk time": "2 h"
        },
        "Body": {
            "Dimensions": "131 x 45 x 21 mm (5.16 x 1.77 x 0.83 in)",
            "SIM": "Mini-SIM",
            "Weight": "170 g (6.00 oz)"
        },
        "Camera": {},
        "Comms": {
            "Bluetooth": "No",
            "GPS": "No",
            "Radio": "No",
            "USB": "",
            "WLAN": "No"
        },
        "Display": {
            "": "- Fixed icons",
            "Resolution": "4 x 12 chars",
            "Size": "",
            "Type": "Monochrome graphic"
        },
        "Features": {
            "Alarm": "No",
            "Browser": "",
            "Clock": "No",
            "Games": "No",
            "Java": "No",
            "Messaging": "SMS"
        },
        "Launch": {
            "Announced": "1999",
            "Status": "Discontinued"
        },
        "Memory": {
            "Call records": "20 dialed calls",
            "Card slot": "No",
            "Phonebook": ""
        },
        "Misc": {
            "0": "C",
            "1": "o",
            "10": ".",
            "11": "g",
            "12": "s",
            "13": "m",
            "14": "a",
            "15": "r",
            "16": "e",
            "17": "n",
            "18": "a",
            "19": ".",
            "2": "l",
            "20": "c",
            "21": "o",
            "22": "m",
            "23": "/",
            "24": "#",
            "3": "o",
            "4": "r",
            "5": "s",
            "6": "/",
            "7": "w",
            "8": "w",
            "9": "w"
        },
        "Network": {
            "2G bands": "GSM 900",
            "EDGE": "No",
            "GPRS": "No",
            "Technology": "GSM"
        },
        "Sound": {
            "3.5mm jack": "No",
            "Alert types": "Monophonic ringtones",
            "Loudspeaker": "No"
        }
    },
    "main": {
        "device_name": "Maxon MX-3204",
        "index": 1,
        "url": "http://www.gsmarena.com/maxon_mx_3204-169.php"
    }
}