{
    "data": {
        "Battery": {
            "": "Li-Ion 1500 mAh battery",
            "Stand-by": "",
            "Talk time": ""
        },
        "Body": {
            "Dimensions": "135 x 67 x 10 mm (5.31 x 2.64 x 0.39 in)",
            "SIM": "Dual SIM",
            "Weight": "-"
        },
        "Camera": {
            "Features": "Geo-tagging",
            "Primary": "3.15 MP, 2048 x 1536 pixels, autofocus, LED flash",
            "Secondary": "VGA",
            "Video": "Yes"
        },
        "Comms": {
            "Bluetooth": "v4.0",
            "GPS": "A-GPS only",
            "Radio": "FM radio",
            "USB": "microUSB v2.0",
            "WLAN": "Wi-Fi 802.11 b/g/n, hotspot"
        },
        "Display": {
            "Multitouch": "Yes",
            "Resolution": "480 x 854 pixels (~218 ppi pixel density)",
            "Size": "4.5 inches (~61.7% screen-to-body ratio)",
            "Type": "TFT capacitive touchscreen, 16M colors"
        },
        "Features": {
            "": "- MP3/AAC/WAV player\n- MP4/H.264 player\n- Document viewer\n- Photo editor",
            "Browser": "HTML",
            "Java": "No",
            "Messaging": "SMS(threaded view), MMS, Email, IM",
            "Sensors": "Accelerometer, proximity, compass"
        },
        "Launch": {
            "Announced": "2014, May",
            "Status": "Available. Released 2014, May"
        },
        "Memory": {
            "Card slot": "microSD, up to 32 GB",
            "Internal": "4 GB, 512 MB RAM"
        },
        "Misc": {
            "Colors": "Black",
            "Price group": "2/10 (About 80 EUR)"
        },
        "Network": {
            "2G bands": "GSM 850 / 900 / 1800 / 1900 - SIM 1 & SIM 2",
            "3G bands": "HSDPA 900 / 2100",
            "EDGE": "Class 12",
            "GPRS": "Class 12",
            "Speed": "HSPA 21.1/5.76 Mbps",
            "Technology": "GSM / HSPA"
        },
        "Platform": {
            "CPU": "Dual-core 1.0 GHz Cortex-A7",
            "Chipset": "Mediatek MT6572",
            "GPU": "Mali-400",
            "OS": "Android OS, v4.2 (Jelly Bean)"
        },
        "Sound": {
            "3.5mm jack": "Yes",
            "Alert types": "Vibration; MP3, WAV ringtones",
            "Loudspeaker": "Yes"
        }
    },
    "main": {
        "device_name": "QMobile Noir A75",
        "image": {
            "href": "http://www.gsmarena.com/qmobile_noir_a75-pictures-7387.php",
            "src": "http://cdn2.gsmarena.com/vv/bigpic/qmobile-noir-a75.jpg"
        },
        "index": 1,
        "url": "http://www.gsmarena.com/qmobile_noir_a75-7387.php"
    }
}