{
    "data": {
        "Battery": {
            "": "",
            "Stand-by": "",
            "Talk time": ""
        },
        "Body": {
            "Dimensions": "91 x 47 x 19.5 mm (3.58 x 1.85 x 0.77 in)",
            "Keyboard": "QWERTY",
            "SIM": "Mini-SIM",
            "Weight": ""
        },
        "Camera": {
            "Primary": "VGA, 640 x 480 pixels",
            "Secondary": "No",
            "Video": "Yes"
        },
        "Comms": {
            "Bluetooth": "v2.0, A2DP",
            "GPS": "No",
            "Radio": "No",
            "USB": "v2.0",
            "WLAN": "No"
        },
        "Display": {
            "": "- Automatic switching display",
            "Resolution": "176 x 220 pixels (~134 ppi pixel density)",
            "Size": "2.1 inches (~32.4% screen-to-body ratio)",
            "Type": "TFT, 65K colors"
        },
        "Features": {
            "Browser": "WAP 2.0/xHTML",
            "Games": "Yes + downloadable",
            "Java": "Yes, MIDP 2.0",
            "Messaging": "SMS, MMS, Instant Messaging"
        },
        "Launch": {
            "Announced": "2007, February",
            "Status": "Cancelled"
        },
        "Memory": {
            "Call records": "20 dialed, 20 received, 20 missed calls",
            "Card slot": "No",
            "Internal": "25 MB",
            "Phonebook": "Yes"
        },
        "Misc": {
            "0": "C",
            "1": "o",
            "10": ".",
            "11": "g",
            "12": "s",
            "13": "m",
            "14": "a",
            "15": "r",
            "16": "e",
            "17": "n",
            "18": "a",
            "19": ".",
            "2": "l",
            "20": "c",
            "21": "o",
            "22": "m",
            "23": "/",
            "24": "#",
            "3": "o",
            "4": "r",
            "5": "s",
            "6": "/",
            "7": "w",
            "8": "w",
            "9": "w"
        },
        "Network": {
            "2G bands": "GSM 900 / 1800 / 1900",
            "EDGE": "Yes",
            "GPRS": "Class 10",
            "Technology": "GSM"
        },
        "Sound": {
            "3.5mm jack": "No",
            "Alert types": "Vibration; Downloadable polyphonic, MP3 ringtones",
            "Loudspeaker": "Yes"
        }
    },
    "main": {
        "device_name": "Samsung P110",
        "image": {
            "href": "http://www.gsmarena.com/samsung_p110-pictures-1868.php",
            "src": "http://cdn2.gsmarena.com/vv/bigpic/samsung-p110.gif"
        },
        "index": 1,
        "url": "http://www.gsmarena.com/samsung_p110-1868.php"
    }
}