{
    "data": {
        "Battery": {
            "": "Li-Ion battery",
            "Stand-by": "Up to 240 h",
            "Talk time": "Up to 4 h"
        },
        "Body": {
            "": "- Flashlight",
            "Dimensions": "107 x 45 x 13 mm (4.21 x 1.77 x 0.51 in)",
            "SIM": "Mini-SIM",
            "Weight": "63 g (2.22 oz)"
        },
        "Camera": {
            "Primary": "VGA, 640 x 480 pixels",
            "Secondary": "No",
            "Video": "No"
        },
        "Comms": {
            "Bluetooth": "Yes",
            "GPS": "No",
            "Radio": "FM radio",
            "USB": "No",
            "WLAN": "No"
        },
        "Display": {
            "Resolution": "-",
            "Size": "1.8 inches (~19.2% screen-to-body ratio)",
            "Type": "TFT"
        },
        "Features": {
            "": "- MP3/3GP player\n- Organizer\n- Unit & currency converter\n- Predictive text input\n- Voice memo",
            "Browser": "WAP 2.0/xHTML",
            "Games": "Yes",
            "Java": "No",
            "Messaging": "SMS, MMS"
        },
        "Launch": {
            "Announced": "2011",
            "Status": "Available. Released 2011"
        },
        "Memory": {
            "Call records": "Yes",
            "Card slot": "microSD",
            "Phonebook": "500 entries"
        },
        "Misc": {
            "0": "C",
            "1": "o",
            "10": ".",
            "11": "g",
            "12": "s",
            "13": "m",
            "14": "a",
            "15": "r",
            "16": "e",
            "17": "n",
            "18": "a",
            "19": ".",
            "2": "l",
            "20": "c",
            "21": "o",
            "22": "m",
            "23": "/",
            "24": "#",
            "3": "o",
            "4": "r",
            "5": "s",
            "6": "/",
            "7": "w",
            "8": "w",
            "9": "w"
        },
        "Network": {
            "": "GSM 850 / 900 / 1800 / 1900 - SIM 2 (optional)",
            "2G bands": "GSM 850 / 900 / 1800 / 1900 - SIM 1",
            "EDGE": "No",
            "GPRS": "Yes",
            "Technology": "GSM"
        },
        "Sound": {
            "3.5mm jack": "No",
            "Alert types": "Vibration; MP3 ringtones",
            "Loudspeaker": "Yes"
        }
    },
    "main": {
        "device_name": "verykool i122",
        "image": {
            "href": "http://www.gsmarena.com/verykool_i122-pictures-4051.php",
            "src": "http://cdn2.gsmarena.com/vv/bigpic/verykool-i122.jpg"
        },
        "index": 1,
        "url": "http://www.gsmarena.com/verykool_i122-4051.php"
    }
}