{
    "data": {
        "Battery": {
            "": "Li-Ion 1450 mAh battery",
            "Stand-by": "Up to 333 h (2G) / Up to 242 h (3G)",
            "Talk time": "Up to 13 h 20 min (2G) / Up to 10 h (3G)"
        },
        "Body": {
            "Dimensions": "118.5 x 63 x 10.7 mm (4.67 x 2.48 x 0.42 in)",
            "SIM": "Dual SIM",
            "Weight": "116 g (4.09 oz)"
        },
        "Camera": {
            "Features": "Geo-tagging, panorama, HDR",
            "Primary": "5 MP, 2592 \u0445 1944 pixels, autofocus, LED flash",
            "Secondary": "VGA",
            "Video": "720p"
        },
        "Comms": {
            "Bluetooth": "v3.0",
            "GPS": "Yes, with A-GPS",
            "Radio": "FM radio",
            "USB": "microUSB v2.0",
            "WLAN": "Wi-Fi 802.11 b/g/n, hotspot"
        },
        "Display": {
            "Multitouch": "Yes",
            "Resolution": "480 x 800 pixels (~233 ppi pixel density)",
            "Size": "4.0 inches (~61.0% screen-to-body ratio)",
            "Type": "TFT capacitive touchscreen, 16M colors"
        },
        "Features": {
            "": "- MP4/WMV/H.264 player\n- MP3/WAV/AAC+ player\n- Document viewer\n- Photo/video editor\n- Voice memo",
            "Browser": "HTML5",
            "Java": "No",
            "Messaging": "SMS(threaded view), MMS, Email, Push Email, IM",
            "Sensors": "Accelerometer, proximity"
        },
        "Launch": {
            "Announced": "2013, November",
            "Status": "Available. Released 2013, November"
        },
        "Memory": {
            "Card slot": "microSD, up to 32 GB",
            "Internal": "4 GB, 1 GB RAM"
        },
        "Misc": {
            "Colors": "White",
            "Price group": "2/10 (About 90 EUR)"
        },
        "Network": {
            "2G bands": "GSM 850 / 900 / 1800 / 1900 - SIM 1 & SIM 2",
            "3G bands": "HSDPA 2100",
            "EDGE": "Yes",
            "GPRS": "Yes",
            "Speed": "HSPA 7.2/5.76 Mbps",
            "Technology": "GSM / HSPA"
        },
        "Platform": {
            "CPU": "Quad-core 1.2 GHz Cortex-A5",
            "Chipset": "Qualcomm MSM8225Q Snapdragon S4 Play",
            "GPU": "Adreno 203",
            "OS": "Android OS, v4.1 (Jelly Bean)"
        },
        "Sound": {
            "3.5mm jack": "Yes",
            "Alert types": "Vibration; MP3, WAV ringtones",
            "Loudspeaker": "Yes"
        }
    },
    "main": {
        "device_name": "XOLO Q500",
        "image": {
            "href": "http://www.gsmarena.com/xolo_q500-pictures-5877.php",
            "src": "http://cdn2.gsmarena.com/vv/bigpic/xolo-q500.jpg"
        },
        "index": 1,
        "url": "http://www.gsmarena.com/xolo_q500-5877.php"
    }
}